zsp_sv/core.cpython-38-x86_64-linux-gnu.so
zsp_sv/__version__.py
zsp_sv/__ext__.py
zsp_sv/pkginfo.py
zsp_sv/__main__.py
zsp_sv/__build_num__.py
zsp_sv/libzsp-sv.so
zsp_sv/__init__.py
zsp_sv/share/include/zsp/sv/IFactory.h
zsp_sv/share/include/zsp/sv/zuspec.sv
zsp_sv/share/include/zsp/sv/FactoryExt.h
zsp_sv/share/include/zsp/sv/zsp_sv/hndl_drop_listener.svh
zsp_sv/share/include/zsp/sv/zsp_sv/empty_addr_trait_s.svh
zsp_sv/share/include/zsp/sv/zsp_sv/empty_executor_trait_s.svh
zsp_sv/share/include/zsp/sv/zsp_sv/obj_type_c.svh
zsp_sv/share/include/zsp/sv/zsp_sv/component_c.svh
zsp_sv/share/include/zsp/sv/zsp_sv/addr_claim_base_s.svh
zsp_sv/share/include/zsp/sv/zsp_sv/activity_traverse_c.svh
zsp_sv/share/include/zsp/sv/zsp_sv/reg_group_c.svh
zsp_sv/share/include/zsp/sv/zsp_sv/backend_api.svh
zsp_sv/share/include/zsp/sv/zsp_sv/sv_cheatsheet.md
zsp_sv/share/include/zsp/sv/zsp_sv/activity_seq_c.svh
zsp_sv/share/include/zsp/sv/zsp_sv/activity_traverse_compound_c.svh
zsp_sv/share/include/zsp/sv/zsp_sv/transparent_addr_region_s.svh
zsp_sv/share/include/zsp/sv/zsp_sv/zsp_sv.sv
zsp_sv/share/include/zsp/sv/zsp_sv/reg_group_field_c.svh
zsp_sv/share/include/zsp/sv/zsp_sv/solve_resource_claim_data_c.svh
zsp_sv/share/include/zsp/sv/zsp_sv/reg_group_field_arr_c.svh
zsp_sv/share/include/zsp/sv/zsp_sv/channel_c.svh
zsp_sv/share/include/zsp/sv/zsp_sv/activity_sel_c.svh
zsp_sv/share/include/zsp/sv/zsp_sv/action_constraint_c.svh
zsp_sv/share/include/zsp/sv/zsp_sv/pool_c.svh
zsp_sv/share/include/zsp/sv/zsp_sv/actor_c.svh
zsp_sv/share/include/zsp/sv/zsp_sv/zuspec_sv.core
zsp_sv/share/include/zsp/sv/zsp_sv/resource_claim_c.svh
zsp_sv/share/include/zsp/sv/zsp_sv/map_c.svh
zsp_sv/share/include/zsp/sv/zsp_sv/activity_par_c.svh
zsp_sv/share/include/zsp/sv/zsp_sv/set_c.svh
zsp_sv/share/include/zsp/sv/zsp_sv/zsp_sv_macros.svh
zsp_sv/share/include/zsp/sv/zsp_sv/storage_handle_s.svh
zsp_sv/share/include/zsp/sv/zsp_sv/addr_space_base_c.svh
zuspec_sv-0.0.5.dist-info/LICENSE
zuspec_sv-0.0.5.dist-info/WHEEL
zuspec_sv-0.0.5.dist-info/RECORD
zuspec_sv-0.0.5.dist-info/top_level.txt
zuspec_sv-0.0.5.dist-info/entry_points.txt
zuspec_sv-0.0.5.dist-info/METADATA
