Metadata-Version: 2.1
Name: zuspec-sv
Version: 0.0.5
Summary: Core ARL data model library
Home-page: https://github.com/zuspec/zuspec-sv
Author: Matthew Ballance
Author-email: matt.ballance@gmail.com
License: Apache 2.0
Keywords: SystemVerilog,Verilog,RTL,Python
License-File: LICENSE
Requires-Dist: zuspec-parser
Requires-Dist: zuspec-fe-parser
Requires-Dist: zuspec-arl-dm
Requires-Dist: zuspec-arl-eval
Requires-Dist: zuspec-cli
